tg_pubsub-0.1.2.dist-info/WHEEL
tg_pubsub-0.1.2.dist-info/top_level.txt
tg_pubsub-0.1.2.dist-info/METADATA
tg_pubsub-0.1.2.dist-info/dependency_links.txt
tg_pubsub-0.1.2.dist-info/RECORD
tg_pubsub-0.1.2.dist-info/metadata.json
tg_pubsub-0.1.2.dist-info/DESCRIPTION.rst
tg_pubsub/models.py
tg_pubsub/protocol.py
tg_pubsub/exceptions.py
tg_pubsub/worker.py
tg_pubsub/messages.py
tg_pubsub/__init__.py
tg_pubsub/config.py
tg_pubsub/pubsub.py
tg_pubsub/management/__init__.py
tg_pubsub/management/commands/pubsub_server.py
tg_pubsub/management/commands/__init__.py
