Metadata-Version: 2.0
Name: tg-pubsub
Version: 0.1.2
Summary: Easy pubsub for django
Home-page: https://github.com/thorgate/tg-pubsub
Author: Thorgate
Author-email: code@thorgate.eu
License: ISCL
Keywords: tg-pubsub,tg_pubsub,pubsub,pub,sub,django,redis,queue
Platform: UNKNOWN
Classifier: Development Status :: 2 - Pre-Alpha
Classifier: Intended Audience :: Developers
Classifier: License :: OSI Approved :: ISC License (ISCL)
Classifier: Natural Language :: English
Classifier: Programming Language :: Python :: 3
Classifier: Programming Language :: Python :: 3.4
Classifier: Programming Language :: Python :: 3.5
Requires-Dist: django (>=1.8,<1.10)
Requires-Dist: djangorestframework (>=3)
Requires-Dist: redis (>=2.10.3)
Requires-Dist: websockets
